tidy_tweet/__init__.py
tidy_tweet/__main__.py
tidy_tweet/_version.py
tidy_tweet/database.py
tidy_tweet/processing.py
tidy_tweet/tweet_mapping.py
tidy_tweet/utilities.py
tidy_tweet-0.4.0.dist-info/LICENSE
tidy_tweet-0.4.0.dist-info/METADATA
tidy_tweet-0.4.0.dist-info/WHEEL
tidy_tweet-0.4.0.dist-info/entry_points.txt
tidy_tweet-0.4.0.dist-info/top_level.txt
tidy_tweet-0.4.0.dist-info/RECORD
