Metadata-Version: 2.1
Name: tidy-tweet
Version: 0.4.0
Summary: Tidies Twitter json collected with Twarc into relational tables
Home-page: https://github.com/QUT-Digital-Observatory/tidy_tweet
Author: QUT Digital Observatory
Author-email: digitalobservatory@qut.edu.au
Project-URL: Bug Tracker, https://github.com/QUT-Digital-Observatory/tidy_tweet/issues
Classifier: Programming Language :: Python :: 3
Classifier: License :: OSI Approved :: MIT License
Classifier: Operating System :: OS Independent
Classifier: Environment :: Console
Classifier: Intended Audience :: Science/Research
Classifier: Topic :: Sociology
Requires-Python: >=3.8
License-File: LICENSE
Requires-Dist: click (>=8.0.3)
Provides-Extra: development
Requires-Dist: nox (>=2021.10.1) ; extra == 'development'
Requires-Dist: pytest ; extra == 'development'
Requires-Dist: flake8 ; extra == 'development'
Requires-Dist: black ; extra == 'development'
